CHANGELOG.txt
LICENSE.txt
MANIFEST.in
README.txt
app.py
requirements.txt
setup.py
wsgi.py
clouday1_extract_aws_metadata/__init__.py
clouday1_extract_aws_metadata/apigw_get_integration.py
clouday1_extract_aws_metadata/apigw_get_resources.py
clouday1_extract_aws_metadata/apigw_get_rest_apis.py
clouday1_extract_aws_metadata/apigw_prepare_node.py
clouday1_extract_aws_metadata/cloudtrail_sfn_start_execution.py
clouday1_extract_aws_metadata/cloudtrail_start_transcription_job.py
clouday1_extract_aws_metadata/cloudtrail_translate_text.py
clouday1_extract_aws_metadata/cloudtrail_waf_createWebACL.py
clouday1_extract_aws_metadata/cloudwatch_describe_log_groups.py
clouday1_extract_aws_metadata/cloudwatch_describe_log_stream.py
clouday1_extract_aws_metadata/cloudwatch_get_cognito_log_event.py
clouday1_extract_aws_metadata/cloudwatch_get_log_event.py
clouday1_extract_aws_metadata/cognito_describe_identity_pools.py
clouday1_extract_aws_metadata/cognito_list_identity_pool.py
clouday1_extract_aws_metadata/cognito_prepare_node.py
clouday1_extract_aws_metadata/ddb_initial_request.py
clouday1_extract_aws_metadata/dynamodb_describe_table.py
clouday1_extract_aws_metadata/dynamodb_list_table.py
clouday1_extract_aws_metadata/dynamodb_list_tags_of_resource.py
clouday1_extract_aws_metadata/dynamodb_prepare_node.py
clouday1_extract_aws_metadata/dynamodb_scan.py
clouday1_extract_aws_metadata/ec2_describe_availability_zones.py
clouday1_extract_aws_metadata/ec2_describe_instances.py
clouday1_extract_aws_metadata/ec2_describe_internet_gateway.py
clouday1_extract_aws_metadata/ec2_describe_network_acls.py
clouday1_extract_aws_metadata/ec2_describe_network_interfaces.py
clouday1_extract_aws_metadata/ec2_describe_route_tables.py
clouday1_extract_aws_metadata/ec2_describe_security_group.py
clouday1_extract_aws_metadata/ec2_describe_subnet.py
clouday1_extract_aws_metadata/ec2_describe_vpc_endpoint.py
clouday1_extract_aws_metadata/ec2_prepare_node.py
clouday1_extract_aws_metadata.egg-info/PKG-INFO
clouday1_extract_aws_metadata.egg-info/SOURCES.txt
clouday1_extract_aws_metadata.egg-info/dependency_links.txt
clouday1_extract_aws_metadata.egg-info/top_level.txt
venv/lib/python3.10/site-packages/Flask-2.1.1.dist-info/entry_points.txt
venv/lib/python3.10/site-packages/Flask-2.1.1.dist-info/top_level.txt
venv/lib/python3.10/site-packages/Flask_Cors-3.0.10.dist-info/top_level.txt
venv/lib/python3.10/site-packages/Jinja2-3.1.1.dist-info/entry_points.txt
venv/lib/python3.10/site-packages/Jinja2-3.1.1.dist-info/top_level.txt
venv/lib/python3.10/site-packages/MarkupSafe-2.1.1.dist-info/top_level.txt
venv/lib/python3.10/site-packages/PyYAML-5.4.1.dist-info/top_level.txt
venv/lib/python3.10/site-packages/Pygments-2.11.2.dist-info/entry_points.txt
venv/lib/python3.10/site-packages/Pygments-2.11.2.dist-info/top_level.txt
venv/lib/python3.10/site-packages/Werkzeug-2.1.1.dist-info/top_level.txt
venv/lib/python3.10/site-packages/autopep8-1.6.0.dist-info/entry_points.txt
venv/lib/python3.10/site-packages/autopep8-1.6.0.dist-info/top_level.txt
venv/lib/python3.10/site-packages/bleach-5.0.0.dist-info/top_level.txt
venv/lib/python3.10/site-packages/bleach/_vendor/html5lib-1.1.dist-info/top_level.txt
venv/lib/python3.10/site-packages/boto3-1.21.23.dist-info/top_level.txt
venv/lib/python3.10/site-packages/botocore-1.24.46.dist-info/LICENSE.txt
venv/lib/python3.10/site-packages/botocore-1.24.46.dist-info/top_level.txt
venv/lib/python3.10/site-packages/certifi-2021.10.8.dist-info/top_level.txt
venv/lib/python3.10/site-packages/charset_normalizer-2.0.12.dist-info/entry_points.txt
venv/lib/python3.10/site-packages/charset_normalizer-2.0.12.dist-info/top_level.txt
venv/lib/python3.10/site-packages/click-8.1.2.dist-info/top_level.txt
venv/lib/python3.10/site-packages/clouday1_extract_aws_metadata-0.0.46.dist-info/LICENSE.txt
venv/lib/python3.10/site-packages/clouday1_extract_aws_metadata-0.0.46.dist-info/top_level.txt
venv/lib/python3.10/site-packages/colorama-0.4.4.dist-info/LICENSE.txt
venv/lib/python3.10/site-packages/colorama-0.4.4.dist-info/top_level.txt
venv/lib/python3.10/site-packages/commonmark-0.9.1.dist-info/entry_points.txt
venv/lib/python3.10/site-packages/commonmark-0.9.1.dist-info/top_level.txt
venv/lib/python3.10/site-packages/docutils-0.15.2.dist-info/COPYING.txt
venv/lib/python3.10/site-packages/docutils-0.15.2.dist-info/top_level.txt
venv/lib/python3.10/site-packages/gunicorn-20.1.0.dist-info/entry_points.txt
venv/lib/python3.10/site-packages/gunicorn-20.1.0.dist-info/top_level.txt
venv/lib/python3.10/site-packages/idna-3.3.dist-info/top_level.txt
venv/lib/python3.10/site-packages/importlib_metadata-4.11.3.dist-info/top_level.txt
venv/lib/python3.10/site-packages/itsdangerous-2.1.2.dist-info/top_level.txt
venv/lib/python3.10/site-packages/jmespath-1.0.0.dist-info/LICENSE.txt
venv/lib/python3.10/site-packages/jmespath-1.0.0.dist-info/top_level.txt
venv/lib/python3.10/site-packages/keyring-23.5.0.dist-info/entry_points.txt
venv/lib/python3.10/site-packages/keyring-23.5.0.dist-info/top_level.txt
venv/lib/python3.10/site-packages/pip-22.0.4.dist-info/LICENSE.txt
venv/lib/python3.10/site-packages/pip-22.0.4.dist-info/entry_points.txt
venv/lib/python3.10/site-packages/pip-22.0.4.dist-info/top_level.txt
venv/lib/python3.10/site-packages/pkginfo-1.8.2.dist-info/LICENSE.txt
venv/lib/python3.10/site-packages/pkginfo-1.8.2.dist-info/entry_points.txt
venv/lib/python3.10/site-packages/pkginfo-1.8.2.dist-info/top_level.txt
venv/lib/python3.10/site-packages/pyasn1-0.4.8.dist-info/top_level.txt
venv/lib/python3.10/site-packages/pycodestyle-2.8.0.dist-info/entry_points.txt
venv/lib/python3.10/site-packages/pycodestyle-2.8.0.dist-info/namespace_packages.txt
venv/lib/python3.10/site-packages/pycodestyle-2.8.0.dist-info/top_level.txt
venv/lib/python3.10/site-packages/python_dateutil-2.8.2.dist-info/top_level.txt
venv/lib/python3.10/site-packages/python_dotenv-0.20.0.dist-info/entry_points.txt
