Metadata-Version: 2.1
Name: clouday1-extract-aws-metadata
Version: 0.0.47
Summary: A tool to extract metadata from AWS
Home-page: UNKNOWN
Author: Brandon Wymer
Author-email: brandon.wymer@rocketmail.com
License: MIT
Keywords: AWSMetadataExtractor
Platform: UNKNOWN
Classifier: Development Status :: 5 - Production/Stable
Classifier: Intended Audience :: Education
Classifier: Operating System :: Microsoft :: Windows :: Windows 10
Classifier: License :: OSI Approved :: MIT License
Classifier: Programming Language :: Python :: 3
License-File: LICENSE.txt
